ssh_tools_common/__init__.py
ssh_tools_common/install_check.py
ssh_tools_suite-2.0.0.data/data/licenses/THIRD_PARTY_LICENSES.md
ssh_tools_suite-2.0.0.dist-info/licenses/LICENSE
ssh_tunnel_manager/__init__.py
ssh_tunnel_manager/__main__.py
ssh_tunnel_manager/core/__init__.py
ssh_tunnel_manager/core/config_manager.py
ssh_tunnel_manager/core/constants.py
ssh_tunnel_manager/core/models.py
ssh_tunnel_manager/core/monitor.py
ssh_tunnel_manager/core/tunnel_process.py
ssh_tunnel_manager/gui/__init__.py
ssh_tunnel_manager/gui/__main__.py
ssh_tunnel_manager/gui/main_window.py
ssh_tunnel_manager/gui/main_window_actions.py
ssh_tunnel_manager/gui/main_window_backup.py
ssh_tunnel_manager/gui/main_window_legacy.py
ssh_tunnel_manager/gui/main_window_modern.py
ssh_tunnel_manager/gui/main_window_professional.py
ssh_tunnel_manager/gui/assets/open_cv_icon.png
ssh_tunnel_manager/gui/assets/vlc_icon.png
ssh_tunnel_manager/gui/assets/vlc_icon.py
ssh_tunnel_manager/gui/components/__init__.py
ssh_tunnel_manager/gui/components/file_operations.py
ssh_tunnel_manager/gui/components/log_widget.py
ssh_tunnel_manager/gui/components/modern_toolbar.py
ssh_tunnel_manager/gui/components/network_scanner.py
ssh_tunnel_manager/gui/components/network_visualizer.py
ssh_tunnel_manager/gui/components/powershell_generator.py
ssh_tunnel_manager/gui/components/professional_toolbar.py
ssh_tunnel_manager/gui/components/rdp_handler.py
ssh_tunnel_manager/gui/components/rtsp_handler.py
ssh_tunnel_manager/gui/components/ssh_key_deployment.py
ssh_tunnel_manager/gui/components/ssh_key_generator.py
ssh_tunnel_manager/gui/components/table_widget.py
ssh_tunnel_manager/gui/components/toolbar.py
ssh_tunnel_manager/gui/dialogs/__init__.py
ssh_tunnel_manager/gui/dialogs/multi_hop_sftp_browser.py
ssh_tunnel_manager/gui/dialogs/password_dialog.py
ssh_tunnel_manager/gui/dialogs/quick_transfer.py
ssh_tunnel_manager/gui/dialogs/rtsp_viewer.py
ssh_tunnel_manager/gui/dialogs/sftp_browser.py
ssh_tunnel_manager/gui/dialogs/tunnel_config.py
ssh_tunnel_manager/gui/styles/__init__.py
ssh_tools_suite-2.0.0.dist-info/METADATA
ssh_tools_suite-2.0.0.dist-info/WHEEL
ssh_tools_suite-2.0.0.dist-info/entry_points.txt
ssh_tools_suite-2.0.0.dist-info/top_level.txt
ssh_tools_suite-2.0.0.dist-info/RECORD
