Metadata-Version: 2.4
Name: ssh-tools-suite
Version: 2.0.0
Summary: Comprehensive SSH Tools Suite with Tunnel Manager and Third-Party Installer
Home-page: https://github.com/NicholasKozma/ssh_tools_suite
Author: Nicholas Kozma
Author-email: Nicholas Kozma <Nicholas.Kozma@us.bosch.com>
License-Expression: MIT
Project-URL: Homepage, https://github.com/NicholasKozma/ssh_tools_suite
Project-URL: Documentation, https://nicholaskozma.github.io/ssh_tools_suite/
Project-URL: Repository, https://github.com/NicholasKozma/ssh_tools_suite.git
Project-URL: Bug Reports, https://github.com/NicholasKozma/ssh_tools_suite/issues
Project-URL: PyPI, https://pypi.org/project/ssh-tools-suite/
Project-URL: Changelog, https://github.com/NicholasKozma/ssh_tools_suite/blob/main/CHANGELOG.md
Keywords: ssh,tunnel,networking,security,gui,rtsp,vpn
Classifier: Development Status :: 5 - Production/Stable
Classifier: Environment :: Win32 (MS Windows)
Classifier: Environment :: X11 Applications :: Qt
Classifier: Intended Audience :: Developers
Classifier: Intended Audience :: System Administrators
Classifier: Operating System :: Microsoft :: Windows
Classifier: Operating System :: POSIX :: Linux
Classifier: Operating System :: MacOS
Classifier: Programming Language :: Python :: 3
Classifier: Programming Language :: Python :: 3.9
Classifier: Programming Language :: Python :: 3.10
Classifier: Programming Language :: Python :: 3.11
Classifier: Programming Language :: Python :: 3.12
Classifier: Topic :: Internet
Classifier: Topic :: System :: Networking
Classifier: Topic :: Security
Classifier: Topic :: Software Development :: Libraries :: Python Modules
Classifier: Topic :: System :: Systems Administration
Requires-Python: >=3.8
License-File: LICENSE
Requires-Dist: PySide6>=6.5.0
Requires-Dist: opencv-python>=4.8.0
Requires-Dist: paramiko>=2.8.0
Requires-Dist: cryptography>=3.4.0
Requires-Dist: requests>=2.28.0
Requires-Dist: psutil>=5.9.0
Requires-Dist: WMI>=1.5.1; sys_platform == "win32"
Requires-Dist: pywin32>=305; sys_platform == "win32"
Provides-Extra: dev
Requires-Dist: pytest>=8.0.0; extra == "dev"
Requires-Dist: pytest-qt>=4.0.0; extra == "dev"
Requires-Dist: pytest-mock>=3.0.0; extra == "dev"
Requires-Dist: pytest-cov>=4.0.0; extra == "dev"
Requires-Dist: black>=22.0.0; extra == "dev"
Requires-Dist: flake8>=6.0.0; extra == "dev"
Requires-Dist: mypy>=1.0.0; extra == "dev"
Requires-Dist: pre-commit>=3.0.0; extra == "dev"
Requires-Dist: pyinstaller>=6.0.0; extra == "dev"
Provides-Extra: docs
Requires-Dist: mkdocs>=1.5.0; extra == "docs"
Requires-Dist: mkdocs-material>=9.0.0; extra == "docs"
Requires-Dist: mkdocstrings[python]>=0.22.0; extra == "docs"
Requires-Dist: mkdocs-gen-files>=0.5.0; extra == "docs"
Requires-Dist: mkdocs-literate-nav>=0.6.0; extra == "docs"
Requires-Dist: mkdocs-section-index>=0.3.0; extra == "docs"
Dynamic: author
Dynamic: home-page
Dynamic: license-file
Dynamic: requires-python
